atuin_graph/__init__.py
atuin_graph/cli.py
atuin_graph/generate_calendar.py
atuin_graph/web.py
atuin_graph-1.1.1.dist-info/METADATA
atuin_graph-1.1.1.dist-info/WHEEL
atuin_graph-1.1.1.dist-info/entry_points.txt
atuin_graph-1.1.1.dist-info/licenses/LICENSE
atuin_graph-1.1.1.dist-info/RECORD
